pyky040.py
pyky040/__init__.py
pyky040/pyky040.py
pyky040/pyky040_test.py
pyky040-0.1.4.dist-info/LICENSE
pyky040-0.1.4.dist-info/METADATA
pyky040-0.1.4.dist-info/WHEEL
pyky040-0.1.4.dist-info/top_level.txt
pyky040-0.1.4.dist-info/RECORD
