Metadata-Version: 2.1
Name: pyky040
Version: 0.1.4
Summary: High-level interface for the KY040 rotary encoder and switch.
Home-page: https://github.com/raphaelyancey/pyKY040
Author: Raphael Yancey
Author-email: pypi@raphaelyancey.fr
License: UNKNOWN
Project-URL: Bug Reports, https://github.com/raphaelyancey/pyKY040/issues
Project-URL: Source, https://github.com/raphaelyancey/pyKY040
Keywords: keyes rotary encoder switch ky040
Platform: UNKNOWN
Provides-Extra: device
